LICENSE
MANIFEST.in
README.rst
setup.py
bin/giotto
giotto/__init__.py
giotto/control.py
giotto/demo.py
giotto/exceptions.py
giotto/keyvalue.py
giotto/middleware.py
giotto/primitives.py
giotto/utils.py
giotto.egg-info/PKG-INFO
giotto.egg-info/SOURCES.txt
giotto.egg-info/dependency_links.txt
giotto.egg-info/requires.txt
giotto.egg-info/top_level.txt
giotto/contrib/__init__.py
giotto/contrib/auth/__init__.py
giotto/contrib/auth/middleware.py
giotto/contrib/auth/models.py
giotto/contrib/auth/programs.py
giotto/contrib/auth/views.py
giotto/contrib/static/__init__.py
giotto/contrib/static/programs.py
giotto/controllers/__init__.py
giotto/controllers/cmd.py
giotto/controllers/http.py
giotto/controllers/irc_.py
giotto/programs/__init__.py
giotto/programs/management.py
giotto/programs/shell.py
giotto/programs/tables.py
giotto/templates/generic.html
giotto/views/__init__.py