Metadata-Version: 1.0
Name: giotto
Version: 0.10.4
Summary: Web development simplified. An MVC framework supporting Python 3.
Home-page: https://github.com/priestc/giotto
Author: Chris Priest
Author-email: cp368202@ohiou.edu
License: LICENSE
Platform: UNKNOWN
Classifier: Development Status :: 5 - Production/Stable
Classifier: Programming Language :: Python
Classifier: Programming Language :: Python :: 2.7
Classifier: Programming Language :: Python :: 3
Classifier: Environment :: Web Environment
Classifier: License :: OSI Approved :: BSD License
Classifier: Topic :: Internet :: WWW/HTTP :: WSGI
Classifier: Topic :: Software Development :: Libraries :: Application Frameworks
Classifier: Topic :: Software Development :: Libraries :: Python Modules
